miniflux_summary_agent/__init__.py
miniflux_summary_agent/__main__.py
miniflux_summary_agent/cli.py
miniflux_summary_agent/config.py
miniflux_summary_agent/core.py
miniflux_summary_agent/fetcher.py
miniflux_summary_agent/logging.py
miniflux_summary_agent/models.py
miniflux_summary_agent/py.typed
miniflux_summary_agent/renderer.py
miniflux_summary_agent/summarizer.py
miniflux_summary_agent/templates/summary.html
miniflux_summary_agent-0.1.0.dist-info/licenses/LICENSE
miniflux_summary_agent-0.1.0.dist-info/METADATA
miniflux_summary_agent-0.1.0.dist-info/WHEEL
miniflux_summary_agent-0.1.0.dist-info/entry_points.txt
miniflux_summary_agent-0.1.0.dist-info/top_level.txt
miniflux_summary_agent-0.1.0.dist-info/RECORD
