Metadata-Version: 2.4
Name: miniflux-summary-agent
Version: 0.1.0
Summary: Summarize Miniflux articles with Ollama
Author-email: trly <travis.lyons@gmail.com>
License-Expression: MIT
Project-URL: Homepage, https://github.com/trly/miniflux-summary-agent
Project-URL: Issues, https://github.com/trly/miniflux-summary-agent/issues
Keywords: rss,miniflux,ollama,summarization,ai,news
Classifier: Development Status :: 4 - Beta
Classifier: Intended Audience :: Developers
Classifier: Intended Audience :: End Users/Desktop
Classifier: Programming Language :: Python :: 3
Classifier: Programming Language :: Python :: 3 :: Only
Classifier: Programming Language :: Python :: 3.10
Classifier: Programming Language :: Python :: 3.11
Classifier: Programming Language :: Python :: 3.12
Classifier: Programming Language :: Python :: 3.13
Classifier: Topic :: Internet :: WWW/HTTP :: Dynamic Content
Classifier: Topic :: Software Development :: Libraries :: Python Modules
Classifier: Topic :: Text Processing :: Markup :: HTML
Classifier: Topic :: Utilities
Requires-Python: >=3.10
License-File: LICENSE
Requires-Dist: beautifulsoup4>=4.13.4
Requires-Dist: python-dotenv>=0.19.0
Requires-Dist: jinja2>=3.1.6
Requires-Dist: miniflux>=1.1.4
Requires-Dist: ollama>=0.5.1
Requires-Dist: playwright>=1.53.0
Requires-Dist: pydantic>=2.0.0
Requires-Dist: requests>=2.32.4
Requires-Dist: httpx>=0.28.1
Provides-Extra: dev
Requires-Dist: pytest>=8.4.1; extra == "dev"
Requires-Dist: pytest-asyncio>=1.1.0; extra == "dev"
Requires-Dist: pytest-cov>=6.0.0; extra == "dev"
Requires-Dist: ruff>=0.12.4; extra == "dev"
Dynamic: license-file
